geth/__init__.py
geth/accounts.py
geth/chain.py
geth/default_blockchain_password
geth/exceptions.py
geth/genesis.json
geth/install.py
geth/main.py
geth/mixins.py
geth/process.py
geth/py.typed
geth/reset.py
geth/types.py
geth/wrapper.py
geth/utils/__init__.py
geth/utils/encoding.py
geth/utils/filesystem.py
geth/utils/networking.py
geth/utils/proc.py
geth/utils/thread.py
geth/utils/timeout.py
geth/utils/validation.py
py_geth-6.2.0.dist-info/licenses/LICENSE
py_geth-6.2.0.dist-info/METADATA
py_geth-6.2.0.dist-info/WHEEL
py_geth-6.2.0.dist-info/top_level.txt
py_geth-6.2.0.dist-info/RECORD
