Metadata-Version: 2.4
Name: py-geth
Version: 6.2.0
Summary: py-geth: Run Go-Ethereum as a subprocess
Home-page: https://github.com/ethereum/py-geth
Author: The Ethereum Foundation
Author-email: snakecharmers@ethereum.org
License: MIT
Keywords: ethereum go-ethereum geth
Classifier: Development Status :: 2 - Pre-Alpha
Classifier: Intended Audience :: Developers
Classifier: License :: OSI Approved :: MIT License
Classifier: Natural Language :: English
Classifier: Programming Language :: Python :: 3
Classifier: Programming Language :: Python :: 3.8
Classifier: Programming Language :: Python :: 3.9
Classifier: Programming Language :: Python :: 3.10
Classifier: Programming Language :: Python :: 3.11
Classifier: Programming Language :: Python :: 3.12
Classifier: Programming Language :: Python :: 3.13
Requires-Python: >=3.8, <4
License-File: LICENSE
Requires-Dist: eval_type_backport>=0.1.0; python_version < "3.10"
Requires-Dist: pydantic>=2.6.0
Requires-Dist: requests>=2.23
Requires-Dist: semantic-version>=2.6.0
Requires-Dist: types-requests>=2.0.0
Requires-Dist: typing-extensions>=4.0.1
Provides-Extra: dev
Requires-Dist: build>=0.9.0; extra == "dev"
Requires-Dist: bump_my_version>=0.19.0; extra == "dev"
Requires-Dist: ipython; extra == "dev"
Requires-Dist: mypy==1.10.0; extra == "dev"
Requires-Dist: pre-commit>=3.4.0; extra == "dev"
Requires-Dist: tox>=4.0.0; extra == "dev"
Requires-Dist: twine; extra == "dev"
Requires-Dist: wheel; extra == "dev"
Requires-Dist: towncrier<25,>=24; extra == "dev"
Requires-Dist: flaky>=3.2.0; extra == "dev"
Requires-Dist: pytest>=7.0.0; extra == "dev"
Requires-Dist: pytest-xdist>=2.4.0; extra == "dev"
Provides-Extra: docs
Requires-Dist: towncrier<25,>=24; extra == "docs"
Provides-Extra: test
Requires-Dist: flaky>=3.2.0; extra == "test"
Requires-Dist: pytest>=7.0.0; extra == "test"
Requires-Dist: pytest-xdist>=2.4.0; extra == "test"
Dynamic: author
Dynamic: author-email
Dynamic: classifier
Dynamic: description
Dynamic: description-content-type
Dynamic: home-page
Dynamic: keywords
Dynamic: license
Dynamic: license-file
Dynamic: provides-extra
Dynamic: requires-dist
Dynamic: requires-python
Dynamic: summary
